alphai/__init__.py
alphai/auth.py
alphai/cleanup.py
alphai/cli.py
alphai/client.py
alphai/config.py
alphai/docker.py
alphai/exceptions.py
alphai/jupyter_manager.py
alphai/notebook_renderer.py
alphai/utils.py
alphai/commands/__init__.py
alphai/commands/config.py
alphai/commands/docker.py
alphai/commands/jupyter.py
alphai/commands/notebooks.py
alphai/commands/orgs.py
alphai/commands/projects.py
alphai-0.2.1.dist-info/METADATA
alphai-0.2.1.dist-info/WHEEL
alphai-0.2.1.dist-info/entry_points.txt
alphai-0.2.1.dist-info/top_level.txt
alphai-0.2.1.dist-info/RECORD
