Metadata-Version: 2.4
Name: alphai
Version: 0.2.1
Summary: A CLI tool and Python package for the runalph.ai platform
Author-email: Andrew Chang <andrew@runalph.ai>
Project-URL: Homepage, https://runalph.ai
Project-URL: Documentation, https://docs.runalph.ai
Project-URL: Repository, https://github.com/alph-ai/alphai
Project-URL: Issues, https://github.com/alph-ai/alphai/issues
Keywords: cli,api,data-science,alph
Classifier: Development Status :: 4 - Beta
Classifier: Intended Audience :: Developers
Classifier: Programming Language :: Python :: 3
Classifier: Programming Language :: Python :: 3.10
Classifier: Programming Language :: Python :: 3.11
Classifier: Programming Language :: Python :: 3.12
Classifier: Programming Language :: Python :: 3.13
Requires-Python: >=3.10
Requires-Dist: click>=8.1.0
Requires-Dist: rich>=13.0.0
Requires-Dist: alph-sdk>=0.5.0
Requires-Dist: httpx>=0.25.0
Requires-Dist: pydantic>=2.0.0
Requires-Dist: questionary>=2.1.0
Requires-Dist: jupyterlab>=4.5.1
Provides-Extra: dev
Requires-Dist: pytest>=7.0.0; extra == "dev"
Requires-Dist: pytest-cov>=4.0.0; extra == "dev"
Requires-Dist: black>=23.0.0; extra == "dev"
Requires-Dist: ruff>=0.1.0; extra == "dev"
Requires-Dist: mypy>=1.5.0; extra == "dev"
